{
  "EN": {
    "enterCode": "Enter Your Access Code",
    "enterName": "Enter your name",
    "continueButton": "Continue",
    "startLetterButton": "Start Letter",
    "nextSentenceButton": "Continue Letter",
    "downloadPDF": "Download PDF",
    "invalidCode": "Invalid code",
    "codeUsed": "This code has already been used.",
    "pdfGreeting": "Dear",
    "pdfEnding": "Your special gift awaits!"
  },
  "ES": {
    "enterCode": "Ingrese su código de acceso",
    "enterName": "Ingrese su nombre",
    "continueButton": "Continuar",
    "startLetterButton": "Iniciar carta",
    "nextSentenceButton": "Continuar carta",
    "downloadPDF": "Descargar PDF",
    "invalidCode": "Código inválido",
    "codeUsed": "Este código ya ha sido usado.",
    "pdfGreeting": "Querido/a",
    "pdfEnding": "¡Su regalo especial lo espera!"
  },
  "DE": {
    "enterCode": "Geben Sie Ihren Zugangscode ein",
    "enterName": "Geben Sie Ihren Namen ein",
    "continueButton": "Weiter",
    "startLetterButton": "Brief starten",
    "nextSentenceButton": "Brief fortsetzen",
    "downloadPDF": "PDF herunterladen",
    "invalidCode": "Ungültiger Code",
    "codeUsed": "Dieser Code wurde bereits verwendet.",
    "pdfGreeting": "Lieber",
    "pdfEnding": "Ihr besonderes Geschenk wartet auf Sie!"
  }
}
